simple_num_operations/__init__.py
simple_num_operations/all.py
simple_num_operations/buildutils_sno.py
simple_num_operations/exceptions_all.py
simple_num_operations/v01.py
simple_num_operations/v02.py
simple_num_operations/v03.py
simple_num_operations-1.1.dist-info/LICENSE
simple_num_operations-1.1.dist-info/METADATA
simple_num_operations-1.1.dist-info/WHEEL
simple_num_operations-1.1.dist-info/top_level.txt
simple_num_operations-1.1.dist-info/RECORD
