Metadata-Version: 2.1
Name: simple-num-operations
Version: 1.1
Summary: This is a package to do some operations with numbers.
Home-page: https://github.com/thedotaxein/simplenumoperations
Author: axeinstd
Author-email: axeinthereal@gmail.com
Classifier: Programming Language :: Python :: 3
Classifier: License :: OSI Approved :: MIT License
Classifier: Operating System :: OS Independent
Requires-Python: >=3.9
License-File: LICENSE
Requires-Dist: colorama
